
[
    {
      "id":"1",
       "catagory_logo" : "social-media 1.png",
       "name":"Creative Design",
       "job_available": "200 jobs available"
    },
    {
      "id":"2",
       "catagory_logo" : "accounts 1.png",
       "name":"accounts & Finance",
       "job_available": "100 jobs available"
    },
    {
      "id":"3",
       "catagory_logo" : "business 1.png",
       "name":"Merketing & Sales ",
       "job_available": "150 jobs available"
    },
    {
      "id":"4",
        "catagory_logo" : "chip 1.png",
        "name":"Engineering Job ",
        "job_available": "224 jobs available"
     }
    
]



